{
  "siteConfigs": {
    "fussell-plumbing": {
      "query": "plumber, 35621, Eva, AL, US",
      "name": "Fussell Plumbing",
      "name_for_emails": "Fussell Plumbing",
      "site": "",
      "subtypes": "Plumber, Service establishment",
      "category": "Plumber",
      "type": "Plumber",
      "phone": "+1 256-505-8606",
      "phone.phones_enricher.carrier_name": "",
      "phone.phones_enricher.carrier_type": "mobile",
      "full_address": "",
      "borough": "",
      "street": "",
      "city": "",
      "postal_code": "",
      "state": "",
      "us_state": "",
      "country": "",
      "country_code": "",
      "latitude": "34.5457189",
      "longitude": "-86.209658",
      "h3": "8944eb2a257ffff",
      "time_zone": "America/Chicago",
      "plus_code": "",
      "area_service": "TRUE",
      "rating": "5",
      "reviews": "6",
      "reviews_link": "https://search.google.com/local/reviews?placeid=ChIJuZ-OPYJp50gRpx_k5KSNLH4&q=plumber,+35621,+Eva,+AL,+US&authuser=0&hl=en&gl=US",
      "reviews_tags": "",
      "reviews_per_score": "",
      "reviews_per_score_1": "0",
      "reviews_per_score_2": "0",
      "reviews_per_score_3": "0",
      "reviews_per_score_4": "0",
      "reviews_per_score_5": "6",
      "photos_count": "5",
      "photo": "https://lh5.googleusercontent.com/p/AF1QipO7gmyRQAh5NKkgSdbe7pibYhtzsthhSBq9xUNy=w800-h500-k-no",
      "street_view": "https://lh5.googleusercontent.com/p/AF1QipO7gmyRQAh5NKkgSdbe7pibYhtzsthhSBq9xUNy=w1600-h1000-k-no",
      "located_in": "",
      "working_hours": "",
      "working_hours_old_format": "",
      "other_hours": "",
      "popular_times": "",
      "business_status": "OPERATIONAL",
      "about": "{}",
      "range": "",
      "posts": "",
      "logo": "https://lh6.googleusercontent.com/-waVkreristc/AAAAAAAAAAI/AAAAAAAAAAA/mgzQqwNRZIQ/photo.jpg",
      "description": "",
      "typical_time_spent": "",
      "verified": "TRUE",
      "owner_id": "112784281818667580690",
      "owner_title": "Fussell Plumbing",
      "owner_link": "https://www.google.com/maps/contrib/112784281818667580690",
      "reservation_links": "",
      "booking_appointment_link": "",
      "menu_link": "",
      "order_links": "",
      "location_link": "https://www.google.com/maps/place/Fussell+Plumbing/@34.5457189,-86.20965799999999,14z/data=!4m8!1m2!2m1!1sFussell+Plumbing!3m4!1s0x48e769823d8e9fb9:0x7e2c8da4e4e41fa7!8m2!3d34.5457189!4d-86.20965799999999",
      "location_reviews_link": "https://www.google.com/maps/place/Fussell+Plumbing/@34.5457189,-86.20965799999999,13.99z/data=!4m16!1m7!3m6!1s0x48e769823d8e9fb9:0x7e2c8da4e4e41fa7!2sFussell+Plumbing!8m2!3d34.5457189!4d-86.20965799999999!16s%2Fg%2F11ckvg1dmb!3m7!1s0x48e769823d8e9fb9:0x7e2c8da4e4e41fa7!8m2!3d34.5457189!4d-86.20965799999999!9m1!1b1!16s%2Fg%2F11ckvg1dmb?entry=ttu",
      "place_id": "ChIJuZ-OPYJp50gRpx_k5KSNLH4",
      "google_id": "0x48e769823d8e9fb9:0x7e2c8da4e4e41fa7",
      "cid": "9.0918E+18",
      "kgmid": "/g/11wj5px6pr",
      "reviews_id": "9091797487108497319",
      "located_google_id": "",
      "email_1": "",
      "email_1.emails_validator.status": "",
      "email_1.emails_validator.status_details": "",
      "email_1_full_name": "",
      "email_1_first_name": "",
      "email_1_last_name": "",
      "email_1_title": "",
      "email_1_phone": "",
      "email_2": "",
      "email_2.emails_validator.status": "",
      "email_2.emails_validator.status_details": "",
      "email_2_full_name": "",
      "email_2_first_name": "",
      "email_2_last_name": "",
      "email_2_title": "",
      "email_2_phone": "",
      "email_3": "",
      "email_3.emails_validator.status": "",
      "email_3.emails_validator.status_details": "",
      "email_3_full_name": "",
      "email_3_first_name": "",
      "email_3_last_name": "",
      "email_3_title": "",
      "email_3_phone": "",
      "phone_1": "",
      "phone_1.phones_enricher.carrier_name": "",
      "phone_1.phones_enricher.carrier_type": "",
      "phone_2": "",
      "phone_3": "",
      "facebook": "",
      "instagram": "",
      "linkedin": "",
      "tiktok": "",
      "medium": "",
      "reddit": "",
      "skype": "",
      "snapchat": "",
      "telegram": "",
      "whatsapp": "",
      "twitter": "",
      "vimeo": "",
      "youtube": "",
      "github": "",
      "crunchbase": "",
      "website_title": "",
      "website_generator": "",
      "website_description": "",
      "website_keywords": "",
      "website_has_fb_pixel": "",
      "website_has_google_tag": "",
      "primaryColor": "#9ad114",
      "secondaryColor": "#668b0d"
    },
    "jason-s-drain-service": {
      "query": "plumber, 35468, Kellerman, AL, US",
      "name": "Jason's Drain Service",
      "name_for_emails": "Jasons Drain Service",
      "site": "",
      "subtypes": "Plumber",
      "category": "Plumber",
      "type": "Plumber",
      "phone": "+1 205-764-8182",
      "phone.phones_enricher.carrier_name": "",
      "phone.phones_enricher.carrier_type": "mobile",
      "full_address": "2010 Mountainbrook Dr, Cottondale, AL 35453",
      "borough": "None",
      "street": "2010 Mountainbrook Dr",
      "city": "Cottondale",
      "postal_code": "35453",
      "state": "Alabama",
      "us_state": "Alabama",
      "country": "United States of America",
      "country_code": "US",
      "latitude": "33.1867702",
      "longitude": "-87.4287397",
      "h3": "8944ed6284fffff",
      "time_zone": "America/Chicago",
      "plus_code": "",
      "area_service": "FALSE",
      "rating": "5",
      "reviews": "24",
      "reviews_link": "https://search.google.com/local/reviews?placeid=ChIJXRkQEk8IhogR_lyzlUctFH4&q=plumber,+35468,+Kellerman,+AL,+US&authuser=0&hl=en&gl=US",
      "reviews_tags": "",
      "reviews_per_score": "",
      "reviews_per_score_1": "0",
      "reviews_per_score_2": "0",
      "reviews_per_score_3": "0",
      "reviews_per_score_4": "1",
      "reviews_per_score_5": "23",
      "photos_count": "5",
      "photo": "https://lh5.googleusercontent.com/p/AF1QipM2NgyFCHFQ2Wf3V39VkgtLEM5RjR9CNDH-rdRi=w800-h500-k-no",
      "street_view": "https://lh5.googleusercontent.com/p/AF1QipM2NgyFCHFQ2Wf3V39VkgtLEM5RjR9CNDH-rdRi=w1600-h1000-k-no",
      "located_in": "",
      "working_hours": "{\"Monday\": \"8AM-5PM\", \"Tuesday\": \"8AM-5PM\", \"Wednesday\": \"8AM-5PM\", \"Thursday\": \"8AM-5PM\", \"Friday\": \"8AM-5PM\", \"Saturday\": \"Closed\", \"Sunday\": \"Closed\"}",
      "working_hours_old_format": "Monday:8AM-5PM|Tuesday:8AM-5PM|Wednesday:8AM-5PM|Thursday:8AM-5PM|Friday:8AM-5PM|Saturday:Closed|Sunday:Closed",
      "other_hours": "",
      "popular_times": "",
      "business_status": "OPERATIONAL",
      "about": "{\"Payments\": {\"Credit cards\": true}}",
      "range": "",
      "posts": "",
      "logo": "https://lh3.googleusercontent.com/-lX3PUhYHCbc/AAAAAAAAAAI/AAAAAAAAAAA/O0cO542tW58/photo.jpg",
      "description": "",
      "typical_time_spent": "",
      "verified": "TRUE",
      "owner_id": "111883325622682532746",
      "owner_title": "Jason's Drain Service",
      "owner_link": "https://www.google.com/maps/contrib/111883325622682532746",
      "reservation_links": "",
      "booking_appointment_link": "",
      "menu_link": "",
      "order_links": "",
      "location_link": "https://www.google.com/maps/place/Jason%27s+Drain+Service/@33.1867702,-87.4287397,14z/data=!4m8!1m2!2m1!1sJason%27s+Drain+Service!3m4!1s0x8886084f1210195d:0x7e142d4795b35cfe!8m2!3d33.1867702!4d-87.4287397",
      "location_reviews_link": "https://www.google.com/maps/place/Jason%27s+Drain+Service/@33.1867702,-87.4287397,13.99z/data=!4m16!1m7!3m6!1s0x8886084f1210195d:0x7e142d4795b35cfe!2sJason%27s+Drain+Service!8m2!3d33.1867702!4d-87.4287397!16s%2Fg%2F11ckvg1dmb!3m7!1s0x8886084f1210195d:0x7e142d4795b35cfe!8m2!3d33.1867702!4d-87.4287397!9m1!1b1!16s%2Fg%2F11ckvg1dmb?entry=ttu",
      "place_id": "ChIJXRkQEk8IhogR_lyzlUctFH4",
      "google_id": "0x8886084f1210195d:0x7e142d4795b35cfe",
      "cid": "9.08494E+18",
      "kgmid": "/g/11c1ldwsj4",
      "reviews_id": "9084936133790620926",
      "located_google_id": "",
      "email_1": "jason6006062@me.com",
      "email_1.emails_validator.status": "INVALID",
      "email_1.emails_validator.status_details": "Invalid SMTP",
      "email_1_full_name": "",
      "email_1_first_name": "",
      "email_1_last_name": "",
      "email_1_title": "",
      "email_1_phone": "",
      "email_2": "",
      "email_2.emails_validator.status": "",
      "email_2.emails_validator.status_details": "",
      "email_2_full_name": "",
      "email_2_first_name": "",
      "email_2_last_name": "",
      "email_2_title": "",
      "email_2_phone": "",
      "email_3": "",
      "email_3.emails_validator.status": "",
      "email_3.emails_validator.status_details": "",
      "email_3_full_name": "",
      "email_3_first_name": "",
      "email_3_last_name": "",
      "email_3_title": "",
      "email_3_phone": "",
      "phone_1": "",
      "phone_1.phones_enricher.carrier_name": "",
      "phone_1.phones_enricher.carrier_type": "",
      "phone_2": "",
      "phone_3": "",
      "facebook": "https://www.facebook.com/jasonsdrainservice/",
      "instagram": "",
      "linkedin": "",
      "tiktok": "",
      "medium": "",
      "reddit": "",
      "skype": "",
      "snapchat": "",
      "telegram": "",
      "whatsapp": "",
      "twitter": "",
      "vimeo": "",
      "youtube": "",
      "github": "",
      "crunchbase": "",
      "website_title": "",
      "website_generator": "",
      "website_description": "",
      "website_keywords": "",
      "website_has_fb_pixel": "",
      "website_has_google_tag": "",
      "primaryColor": "#9ad114",
      "secondaryColor": "#668b0d"
    },
    "salser-plumbing-and-septic-service-llc": {
      "query": "plumber, 35078, Harpersville, AL, US",
      "name": "Salser Plumbing and Septic Service, LLC",
      "name_for_emails": "Salser Plumbing And Septic Service",
      "site": "",
      "subtypes": "Plumber, Service establishment",
      "category": "Plumber",
      "type": "Plumber",
      "phone": "+1 205-965-0444",
      "phone.phones_enricher.carrier_name": "",
      "phone.phones_enricher.carrier_type": "mobile",
      "full_address": "",
      "borough": "",
      "street": "",
      "city": "",
      "postal_code": "",
      "state": "",
      "us_state": "",
      "country": "",
      "country_code": "",
      "latitude": "33.3590795",
      "longitude": "-86.4107025",
      "h3": "8944e80cb6fffff",
      "time_zone": "America/Chicago",
      "plus_code": "",
      "area_service": "TRUE",
      "rating": "4.1",
      "reviews": "8",
      "reviews_link": "https://search.google.com/local/reviews?placeid=ChIJwYPAOodCiYgRDaWtJdGuPIs&q=plumber,+35078,+Harpersville,+AL,+US&authuser=0&hl=en&gl=US",
      "reviews_tags": "",
      "reviews_per_score": "",
      "reviews_per_score_1": "1",
      "reviews_per_score_2": "1",
      "reviews_per_score_3": "0",
      "reviews_per_score_4": "0",
      "reviews_per_score_5": "6",
      "photos_count": "5",
      "photo": "https://lh5.googleusercontent.com/p/AF1QipONTXpLKKLFYsdGdCMpcBOxV8ZmhVZjlc5tV3id=w800-h500-k-no",
      "street_view": "https://lh5.googleusercontent.com/p/AF1QipONTXpLKKLFYsdGdCMpcBOxV8ZmhVZjlc5tV3id=w1600-h1000-k-no",
      "located_in": "",
      "working_hours": "",
      "working_hours_old_format": "",
      "other_hours": "",
      "popular_times": "",
      "business_status": "OPERATIONAL",
      "about": "{\"Payments\": {\"Credit cards\": true}}",
      "range": "",
      "posts": "",
      "logo": "https://lh5.googleusercontent.com/-xPmd_-MZ6d4/AAAAAAAAAAI/AAAAAAAAAAA/SCMYUc3djVE/photo.jpg",
      "description": "",
      "typical_time_spent": "",
      "verified": "TRUE",
      "owner_id": "106636071458884307593",
      "owner_title": "Salser Plumbing and Septic Service, LLC",
      "owner_link": "https://www.google.com/maps/contrib/106636071458884307593",
      "reservation_links": "",
      "booking_appointment_link": "",
      "menu_link": "",
      "order_links": "",
      "location_link": "https://www.google.com/maps/place/Salser+Plumbing+and+Septic+Service%2C+LLC/@33.3590795,-86.4107025,14z/data=!4m8!1m2!2m1!1sSalser+Plumbing+and+Septic+Service%2C+LLC!3m4!1s0x888942873ac083c1:0x8b3caed125ada50d!8m2!3d33.3590795!4d-86.4107025",
      "location_reviews_link": "https://www.google.com/maps/place/Salser+Plumbing+and+Septic+Service%2C+LLC/@33.3590795,-86.4107025,13.99z/data=!4m16!1m7!3m6!1s0x888942873ac083c1:0x8b3caed125ada50d!2sSalser+Plumbing+and+Septic+Service%2C+LLC!8m2!3d33.3590795!4d-86.4107025!16s%2Fg%2F11ckvg1dmb!3m7!1s0x888942873ac083c1:0x8b3caed125ada50d!8m2!3d33.3590795!4d-86.4107025!9m1!1b1!16s%2Fg%2F11ckvg1dmb?entry=ttu",
      "place_id": "ChIJwYPAOodCiYgRDaWtJdGuPIs",
      "google_id": "0x888942873ac083c1:0x8b3caed125ada50d",
      "cid": "1.00331E+19",
      "kgmid": "/g/1tg6wgf8",
      "reviews_id": "-8413657790531394291",
      "located_google_id": "",
      "email_1": "",
      "email_1.emails_validator.status": "",
      "email_1.emails_validator.status_details": "",
      "email_1_full_name": "",
      "email_1_first_name": "",
      "email_1_last_name": "",
      "email_1_title": "",
      "email_1_phone": "",
      "email_2": "",
      "email_2.emails_validator.status": "",
      "email_2.emails_validator.status_details": "",
      "email_2_full_name": "",
      "email_2_first_name": "",
      "email_2_last_name": "",
      "email_2_title": "",
      "email_2_phone": "",
      "email_3": "",
      "email_3.emails_validator.status": "",
      "email_3.emails_validator.status_details": "",
      "email_3_full_name": "",
      "email_3_first_name": "",
      "email_3_last_name": "",
      "email_3_title": "",
      "email_3_phone": "",
      "phone_1": "",
      "phone_1.phones_enricher.carrier_name": "",
      "phone_1.phones_enricher.carrier_type": "",
      "phone_2": "",
      "phone_3": "",
      "facebook": "",
      "instagram": "",
      "linkedin": "",
      "tiktok": "",
      "medium": "",
      "reddit": "",
      "skype": "",
      "snapchat": "",
      "telegram": "",
      "whatsapp": "",
      "twitter": "",
      "vimeo": "",
      "youtube": "",
      "github": "",
      "crunchbase": "",
      "website_title": "",
      "website_generator": "",
      "website_description": "",
      "website_keywords": "",
      "website_has_fb_pixel": "",
      "website_has_google_tag": "",
      "primaryColor": "#4663b8",
      "secondaryColor": "#8c8c7c"
    },
    "hydrotech-plumbing-llc": {
      "query": "plumber, 35087, Joppa, AL, US",
      "name": "HydroTech Plumbing LLC",
      "name_for_emails": "Hydrotech Plumbing",
      "site": "",
      "subtypes": "Plumber, Service establishment",
      "category": "Plumber",
      "type": "Plumber",
      "phone": "+1 256-572-9349",
      "phone.phones_enricher.carrier_name": "CELLCO PARTNERSHIP DBA VERIZON WIRELESS - AL",
      "phone.phones_enricher.carrier_type": "mobile",
      "full_address": "",
      "borough": "",
      "street": "",
      "city": "",
      "postal_code": "",
      "state": "",
      "us_state": "",
      "country": "",
      "country_code": "",
      "latitude": "34.349608",
      "longitude": "-86.319824",
      "h3": "8944eb04823ffff",
      "time_zone": "America/Chicago",
      "plus_code": "",
      "area_service": "TRUE",
      "rating": "5",
      "reviews": "9",
      "reviews_link": "https://search.google.com/local/reviews?placeid=ChIJ0dUplGv_iYgRm4hjeLCoORw&q=plumber,+35087,+Joppa,+AL,+US&authuser=0&hl=en&gl=US",
      "reviews_tags": "",
      "reviews_per_score": "",
      "reviews_per_score_1": "0",
      "reviews_per_score_2": "0",
      "reviews_per_score_3": "0",
      "reviews_per_score_4": "0",
      "reviews_per_score_5": "9",
      "photos_count": "5",
      "photo": "https://lh5.googleusercontent.com/p/AF1QipMKIjLx5HXwTKXQnLZhyOCWQ2iGZO6pEgdH-LrW=w800-h500-k-no",
      "street_view": "https://lh5.googleusercontent.com/p/AF1QipMKIjLx5HXwTKXQnLZhyOCWQ2iGZO6pEgdH-LrW=w1600-h1000-k-no",
      "located_in": "",
      "working_hours": "{\"Monday\": \"8AM-5PM\", \"Tuesday\": \"8AM-5PM\", \"Wednesday\": \"8AM-5PM\", \"Thursday\": \"8AM-5PM\", \"Friday\": \"8AM-5PM\", \"Saturday\": \"Closed\", \"Sunday\": \"Closed\"}",
      "working_hours_old_format": "Monday:8AM-5PM|Tuesday:8AM-5PM|Wednesday:8AM-5PM|Thursday:8AM-5PM|Friday:8AM-5PM|Saturday:Closed|Sunday:Closed",
      "other_hours": "",
      "popular_times": "",
      "business_status": "OPERATIONAL",
      "about": "{}",
      "range": "",
      "posts": "",
      "logo": "https://lh6.googleusercontent.com/-buuldVqsHuA/AAAAAAAAAAI/AAAAAAAAAAA/0MnU22efhLQ/photo.jpg",
      "description": "",
      "typical_time_spent": "",
      "verified": "TRUE",
      "owner_id": "100886873039458446061",
      "owner_title": "HydroTech Plumbing LLC",
      "owner_link": "https://www.google.com/maps/contrib/100886873039458446061",
      "reservation_links": "",
      "booking_appointment_link": "",
      "menu_link": "",
      "order_links": "",
      "location_link": "https://www.google.com/maps/place/HydroTech+Plumbing+LLC/@34.349607999999996,-86.319824,14z/data=!4m8!1m2!2m1!1sHydroTech+Plumbing+LLC!3m4!1s0x8889ff6b9429d5d1:0x1c39a8b07863889b!8m2!3d34.349607999999996!4d-86.319824",
      "location_reviews_link": "https://www.google.com/maps/place/HydroTech+Plumbing+LLC/@34.349607999999996,-86.319824,13.99z/data=!4m16!1m7!3m6!1s0x8889ff6b9429d5d1:0x1c39a8b07863889b!2sHydroTech+Plumbing+LLC!8m2!3d34.349607999999996!4d-86.319824!16s%2Fg%2F11ckvg1dmb!3m7!1s0x8889ff6b9429d5d1:0x1c39a8b07863889b!8m2!3d34.349607999999996!4d-86.319824!9m1!1b1!16s%2Fg%2F11ckvg1dmb?entry=ttu",
      "place_id": "ChIJ0dUplGv_iYgRm4hjeLCoORw",
      "google_id": "0x8889ff6b9429d5d1:0x1c39a8b07863889b",
      "cid": "2.03384E+18",
      "kgmid": "/g/11j7gtczrv",
      "reviews_id": "2033842182621989019",
      "located_google_id": "",
      "email_1": "",
      "email_1.emails_validator.status": "",
      "email_1.emails_validator.status_details": "",
      "email_1_full_name": "",
      "email_1_first_name": "",
      "email_1_last_name": "",
      "email_1_title": "",
      "email_1_phone": "",
      "email_2": "",
      "email_2.emails_validator.status": "",
      "email_2.emails_validator.status_details": "",
      "email_2_full_name": "",
      "email_2_first_name": "",
      "email_2_last_name": "",
      "email_2_title": "",
      "email_2_phone": "",
      "email_3": "",
      "email_3.emails_validator.status": "",
      "email_3.emails_validator.status_details": "",
      "email_3_full_name": "",
      "email_3_first_name": "",
      "email_3_last_name": "",
      "email_3_title": "",
      "email_3_phone": "",
      "phone_1": "",
      "phone_1.phones_enricher.carrier_name": "",
      "phone_1.phones_enricher.carrier_type": "",
      "phone_2": "",
      "phone_3": "",
      "facebook": "",
      "instagram": "",
      "linkedin": "",
      "tiktok": "",
      "medium": "",
      "reddit": "",
      "skype": "",
      "snapchat": "",
      "telegram": "",
      "whatsapp": "",
      "twitter": "",
      "vimeo": "",
      "youtube": "",
      "github": "",
      "crunchbase": "",
      "website_title": "",
      "website_generator": "",
      "website_description": "",
      "website_keywords": "",
      "website_has_fb_pixel": "",
      "website_has_google_tag": "",
      "primaryColor": "#9ad114",
      "secondaryColor": "#668b0d"
    },
    "strickland-plumbing-maintenance": {
      "query": "plumber, 35111, Mc Calla, AL, US",
      "name": "Strickland Plumbing & Maintenance",
      "name_for_emails": "Strickland Plumbing And Maintenance",
      "site": "",
      "subtypes": "Plumber, Service establishment, Home improvement store",
      "category": "Plumber",
      "type": "Plumber",
      "phone": "+1 205-368-0503",
      "phone.phones_enricher.carrier_name": "",
      "phone.phones_enricher.carrier_type": "mobile",
      "full_address": "",
      "borough": "",
      "street": "",
      "city": "",
      "postal_code": "",
      "state": "",
      "us_state": "",
      "country": "",
      "country_code": "",
      "latitude": "33.4309505",
      "longitude": "-86.8413174",
      "h3": "8944e83634fffff",
      "time_zone": "America/Chicago",
      "plus_code": "",
      "area_service": "TRUE",
      "rating": "4.6",
      "reviews": "16",
      "reviews_link": "https://search.google.com/local/reviews?placeid=ChIJTxBP5nIjiYgRbG-KkLQzTZw&q=plumber,+35111,+Mc+Calla,+AL,+US&authuser=0&hl=en&gl=US",
      "reviews_tags": "",
      "reviews_per_score": "",
      "reviews_per_score_1": "1",
      "reviews_per_score_2": "1",
      "reviews_per_score_3": "0",
      "reviews_per_score_4": "0",
      "reviews_per_score_5": "14",
      "photos_count": "5",
      "photo": "https://lh5.googleusercontent.com/p/AF1QipOFkzjDhy_1qrg0o59cOZoYTAvptn2vo0ZGE7Yf=w800-h500-k-no",
      "street_view": "https://lh5.googleusercontent.com/p/AF1QipOFkzjDhy_1qrg0o59cOZoYTAvptn2vo0ZGE7Yf=w1600-h1000-k-no",
      "located_in": "",
      "working_hours": "{\"Monday\": \"8AM-5PM\", \"Tuesday\": \"8AM-5PM\", \"Wednesday\": \"8AM-5PM\", \"Thursday\": \"8AM-5PM\", \"Friday\": \"8AM-5PM\", \"Saturday\": \"Closed\", \"Sunday\": \"Closed\"}",
      "working_hours_old_format": "Monday:8AM-5PM|Tuesday:8AM-5PM|Wednesday:8AM-5PM|Thursday:8AM-5PM|Friday:8AM-5PM|Saturday:Closed|Sunday:Closed",
      "other_hours": "",
      "popular_times": "",
      "business_status": "OPERATIONAL",
      "about": "{}",
      "range": "",
      "posts": "",
      "logo": "https://lh3.googleusercontent.com/-Hbw7gww0joQ/AAAAAAAAAAI/AAAAAAAAAAA/Jfe49m_Yo-k/photo.jpg",
      "description": "",
      "typical_time_spent": "",
      "verified": "TRUE",
      "owner_id": "106043857980628177993",
      "owner_title": "Strickland Plumbing & Maintenance",
      "owner_link": "https://www.google.com/maps/contrib/106043857980628177993",
      "reservation_links": "",
      "booking_appointment_link": "",
      "menu_link": "",
      "order_links": "",
      "location_link": "https://www.google.com/maps/place/Strickland+Plumbing+%26+Maintenance/@33.4309505,-86.8413174,14z/data=!4m8!1m2!2m1!1sStrickland+Plumbing+%26+Maintenance!3m4!1s0x88892372e64f104f:0x9c4d33b4908a6f6c!8m2!3d33.4309505!4d-86.8413174",
      "location_reviews_link": "https://www.google.com/maps/place/Strickland+Plumbing+%26+Maintenance/@33.4309505,-86.8413174,13.99z/data=!4m16!1m7!3m6!1s0x88892372e64f104f:0x9c4d33b4908a6f6c!2sStrickland+Plumbing+%26+Maintenance!8m2!3d33.4309505!4d-86.8413174!16s%2Fg%2F11ckvg1dmb!3m7!1s0x88892372e64f104f:0x9c4d33b4908a6f6c!8m2!3d33.4309505!4d-86.8413174!9m1!1b1!16s%2Fg%2F11ckvg1dmb?entry=ttu",
      "place_id": "ChIJTxBP5nIjiYgRbG-KkLQzTZw",
      "google_id": "0x88892372e64f104f:0x9c4d33b4908a6f6c",
      "cid": "1.12627E+19",
      "kgmid": "/g/11f6xky2ch",
      "reviews_id": "-7184028979973951636",
      "located_google_id": "",
      "email_1": "",
      "email_1.emails_validator.status": "",
      "email_1.emails_validator.status_details": "",
      "email_1_full_name": "",
      "email_1_first_name": "",
      "email_1_last_name": "",
      "email_1_title": "",
      "email_1_phone": "",
      "email_2": "",
      "email_2.emails_validator.status": "",
      "email_2.emails_validator.status_details": "",
      "email_2_full_name": "",
      "email_2_first_name": "",
      "email_2_last_name": "",
      "email_2_title": "",
      "email_2_phone": "",
      "email_3": "",
      "email_3.emails_validator.status": "",
      "email_3.emails_validator.status_details": "",
      "email_3_full_name": "",
      "email_3_first_name": "",
      "email_3_last_name": "",
      "email_3_title": "",
      "email_3_phone": "",
      "phone_1": "",
      "phone_1.phones_enricher.carrier_name": "",
      "phone_1.phones_enricher.carrier_type": "",
      "phone_2": "",
      "phone_3": "",
      "facebook": "",
      "instagram": "",
      "linkedin": "",
      "tiktok": "",
      "medium": "",
      "reddit": "",
      "skype": "",
      "snapchat": "",
      "telegram": "",
      "whatsapp": "",
      "twitter": "",
      "vimeo": "",
      "youtube": "",
      "github": "",
      "crunchbase": "",
      "website_title": "",
      "website_generator": "",
      "website_description": "",
      "website_keywords": "",
      "website_has_fb_pixel": "",
      "website_has_google_tag": "",
      "primaryColor": "#d49884",
      "secondaryColor": "#b98c86"
    },
    "reese-plumbing-llc": {
      "query": "plumber, 36057, Mount Meigs, AL, US",
      "name": "Reese Plumbing LLC",
      "name_for_emails": "Reese Plumbing",
      "site": "",
      "subtypes": "Plumber, Service establishment",
      "category": "Plumber",
      "type": "Plumber",
      "phone": "+1 334-430-6864",
      "phone.phones_enricher.carrier_name": "CELLCO PARTNERSHIP DBA VERIZON WIRELESS - AL",
      "phone.phones_enricher.carrier_type": "mobile",
      "full_address": "",
      "borough": "",
      "street": "",
      "city": "",
      "postal_code": "",
      "state": "",
      "us_state": "",
      "country": "",
      "country_code": "",
      "latitude": "32.490317",
      "longitude": "-85.912168",
      "h3": "8944eeaf3c7ffff",
      "time_zone": "America/Chicago",
      "plus_code": "",
      "area_service": "TRUE",
      "rating": "5",
      "reviews": "17",
      "reviews_link": "https://search.google.com/local/reviews?placeid=ChIJkUsHLO-S6k4RquPYl5V1n54&q=plumber,+36057,+Mount+Meigs,+AL,+US&authuser=0&hl=en&gl=US",
      "reviews_tags": "",
      "reviews_per_score": "",
      "reviews_per_score_1": "0",
      "reviews_per_score_2": "0",
      "reviews_per_score_3": "0",
      "reviews_per_score_4": "0",
      "reviews_per_score_5": "17",
      "photos_count": "5",
      "photo": "https://lh5.googleusercontent.com/p/AF1QipOAJ72tj1f6GsfnW7HEV-f3DAPNxPOGpEjQtU5z=w800-h500-k-no",
      "street_view": "https://lh5.googleusercontent.com/p/AF1QipOAJ72tj1f6GsfnW7HEV-f3DAPNxPOGpEjQtU5z=w1600-h1000-k-no",
      "located_in": "",
      "working_hours": "{\"Monday\": \"Open 24 hours\", \"Tuesday\": \"Open 24 hours\", \"Wednesday\": \"Open 24 hours\", \"Thursday\": \"Open 24 hours\", \"Friday\": \"Open 24 hours\", \"Saturday\": \"Open 24 hours\", \"Sunday\": \"Open 24 hours\"}",
      "working_hours_old_format": "Monday:Open 24 hours|Tuesday:Open 24 hours|Wednesday:Open 24 hours|Thursday:Open 24 hours|Friday:Open 24 hours|Saturday:Open 24 hours|Sunday:Open 24 hours",
      "other_hours": "",
      "popular_times": "",
      "business_status": "OPERATIONAL",
      "about": "{}",
      "range": "",
      "posts": "",
      "logo": "https://lh4.googleusercontent.com/-I5cKSOJiRoU/AAAAAAAAAAI/AAAAAAAAAAA/PGxqO3lBv_Y/photo.jpg",
      "description": "",
      "typical_time_spent": "",
      "verified": "TRUE",
      "owner_id": "103885184408780858395",
      "owner_title": "Reese Plumbing LLC",
      "owner_link": "https://www.google.com/maps/contrib/103885184408780858395",
      "reservation_links": "",
      "booking_appointment_link": "",
      "menu_link": "",
      "order_links": "",
      "location_link": "https://www.google.com/maps/place/Reese+Plumbing+LLC/@32.490317,-85.912168,14z/data=!4m8!1m2!2m1!1sReese+Plumbing+LLC!3m4!1s0x4eea92ef2c074b91:0x9e9f759597d8e3aa!8m2!3d32.490317!4d-85.912168",
      "location_reviews_link": "https://www.google.com/maps/place/Reese+Plumbing+LLC/@32.490317,-85.912168,13.99z/data=!4m16!1m7!3m6!1s0x4eea92ef2c074b91:0x9e9f759597d8e3aa!2sReese+Plumbing+LLC!8m2!3d32.490317!4d-85.912168!16s%2Fg%2F11ckvg1dmb!3m7!1s0x4eea92ef2c074b91:0x9e9f759597d8e3aa!8m2!3d32.490317!4d-85.912168!9m1!1b1!16s%2Fg%2F11ckvg1dmb?entry=ttu",
      "place_id": "ChIJkUsHLO-S6k4RquPYl5V1n54",
      "google_id": "0x4eea92ef2c074b91:0x9e9f759597d8e3aa",
      "cid": "1.143E+19",
      "kgmid": "/g/11r_cxtldb",
      "reviews_id": "-7016760409061792854",
      "located_google_id": "",
      "email_1": "reeseplumbingllc@gmail.com",
      "email_1.emails_validator.status": "RECEIVING",
      "email_1.emails_validator.status_details": "SMTP validated",
      "email_1_full_name": "",
      "email_1_first_name": "",
      "email_1_last_name": "",
      "email_1_title": "",
      "email_1_phone": "",
      "email_2": "",
      "email_2.emails_validator.status": "",
      "email_2.emails_validator.status_details": "",
      "email_2_full_name": "",
      "email_2_first_name": "",
      "email_2_last_name": "",
      "email_2_title": "",
      "email_2_phone": "",
      "email_3": "",
      "email_3.emails_validator.status": "",
      "email_3.emails_validator.status_details": "",
      "email_3_full_name": "",
      "email_3_first_name": "",
      "email_3_last_name": "",
      "email_3_title": "",
      "email_3_phone": "",
      "phone_1": "13344306864",
      "phone_1.phones_enricher.carrier_name": "CELLCO PARTNERSHIP DBA VERIZON WIRELESS - AL",
      "phone_1.phones_enricher.carrier_type": "mobile",
      "phone_2": "",
      "phone_3": "",
      "facebook": "https://www.facebook.com/people/Reese-Plumbing-LLC/100071778456358/",
      "instagram": "",
      "linkedin": "",
      "tiktok": "",
      "medium": "",
      "reddit": "",
      "skype": "",
      "snapchat": "",
      "telegram": "",
      "whatsapp": "",
      "twitter": "",
      "vimeo": "",
      "youtube": "",
      "github": "",
      "crunchbase": "",
      "website_title": "",
      "website_generator": "",
      "website_description": "",
      "website_keywords": "",
      "website_has_fb_pixel": "",
      "website_has_google_tag": "",
      "primaryColor": "#9ad114",
      "secondaryColor": "#668b0d"
    },
    "alabama-water-heater": {
      "query": "plumber, 35741, Brownsboro, AL, US",
      "name": "Alabama Water Heater",
      "name_for_emails": "Alabama Water Heater",
      "site": "",
      "subtypes": "Plumber, Service establishment",
      "category": "Plumber",
      "type": "Plumber",
      "phone": "+1 256-656-5873",
      "phone.phones_enricher.carrier_name": "CELLCO PARTNERSHIP DBA VERIZON WIRELESS - AL",
      "phone.phones_enricher.carrier_type": "mobile",
      "full_address": "",
      "borough": "",
      "street": "",
      "city": "",
      "postal_code": "",
      "state": "",
      "us_state": "",
      "country": "",
      "country_code": "",
      "latitude": "34.7321355",
      "longitude": "-86.6319669",
      "h3": "892649ace73ffff",
      "time_zone": "America/Chicago",
      "plus_code": "",
      "area_service": "TRUE",
      "rating": "5",
      "reviews": "1",
      "reviews_link": "https://search.google.com/local/reviews?placeid=ChIJZzrnrdJbJUURCoYIf9V7sFY&q=plumber,+35741,+Brownsboro,+AL,+US&authuser=0&hl=en&gl=US",
      "reviews_tags": "",
      "reviews_per_score": "",
      "reviews_per_score_1": "0",
      "reviews_per_score_2": "0",
      "reviews_per_score_3": "0",
      "reviews_per_score_4": "0",
      "reviews_per_score_5": "1",
      "photos_count": "5",
      "photo": "https://lh5.googleusercontent.com/p/AF1QipPghHL2xnOFTSEYP7_EKap2PSpiKGm8TnW-DG6u=w800-h500-k-no",
      "street_view": "https://lh5.googleusercontent.com/p/AF1QipPghHL2xnOFTSEYP7_EKap2PSpiKGm8TnW-DG6u=w1600-h1000-k-no",
      "located_in": "",
      "working_hours": "{\"Monday\": \"Open 24 hours\", \"Tuesday\": \"Open 24 hours\", \"Wednesday\": \"Open 24 hours\", \"Thursday\": \"Open 24 hours\", \"Friday\": \"Open 24 hours\", \"Saturday\": \"Open 24 hours\", \"Sunday\": \"Open 24 hours\"}",
      "working_hours_old_format": "Monday:Open 24 hours|Tuesday:Open 24 hours|Wednesday:Open 24 hours|Thursday:Open 24 hours|Friday:Open 24 hours|Saturday:Open 24 hours|Sunday:Open 24 hours",
      "other_hours": "",
      "popular_times": "",
      "business_status": "OPERATIONAL",
      "about": "{\"Service options\": {\"Online estimates\": true}}",
      "range": "",
      "posts": "",
      "logo": "https://lh6.googleusercontent.com/-q_kdULnITNA/AAAAAAAAAAI/AAAAAAAAAAA/b6pUO5tusYE/photo.jpg",
      "description": "",
      "typical_time_spent": "",
      "verified": "TRUE",
      "owner_id": "112268319896047304622",
      "owner_title": "Alabama Water Heater",
      "owner_link": "https://www.google.com/maps/contrib/112268319896047304622",
      "reservation_links": "",
      "booking_appointment_link": "",
      "menu_link": "",
      "order_links": "",
      "location_link": "https://www.google.com/maps/place/Alabama+Water+Heater/@34.7321355,-86.6319669,14z/data=!4m8!1m2!2m1!1sAlabama+Water+Heater!3m4!1s0x45255bd2ade73a67:0x56b07bd57f08860a!8m2!3d34.7321355!4d-86.6319669",
      "location_reviews_link": "https://www.google.com/maps/place/Alabama+Water+Heater/@34.7321355,-86.6319669,13.99z/data=!4m16!1m7!3m6!1s0x45255bd2ade73a67:0x56b07bd57f08860a!2sAlabama+Water+Heater!8m2!3d34.7321355!4d-86.6319669!16s%2Fg%2F11ckvg1dmb!3m7!1s0x45255bd2ade73a67:0x56b07bd57f08860a!8m2!3d34.7321355!4d-86.6319669!9m1!1b1!16s%2Fg%2F11ckvg1dmb?entry=ttu",
      "place_id": "ChIJZzrnrdJbJUURCoYIf9V7sFY",
      "google_id": "0x45255bd2ade73a67:0x56b07bd57f08860a",
      "cid": "6.24663E+18",
      "kgmid": "/g/11rcdw9phx",
      "reviews_id": "6246628840052393482",
      "located_google_id": "",
      "email_1": "",
      "email_1.emails_validator.status": "",
      "email_1.emails_validator.status_details": "",
      "email_1_full_name": "",
      "email_1_first_name": "",
      "email_1_last_name": "",
      "email_1_title": "",
      "email_1_phone": "",
      "email_2": "",
      "email_2.emails_validator.status": "",
      "email_2.emails_validator.status_details": "",
      "email_2_full_name": "",
      "email_2_first_name": "",
      "email_2_last_name": "",
      "email_2_title": "",
      "email_2_phone": "",
      "email_3": "",
      "email_3.emails_validator.status": "",
      "email_3.emails_validator.status_details": "",
      "email_3_full_name": "",
      "email_3_first_name": "",
      "email_3_last_name": "",
      "email_3_title": "",
      "email_3_phone": "",
      "phone_1": "",
      "phone_1.phones_enricher.carrier_name": "",
      "phone_1.phones_enricher.carrier_type": "",
      "phone_2": "",
      "phone_3": "",
      "facebook": "",
      "instagram": "",
      "linkedin": "",
      "tiktok": "",
      "medium": "",
      "reddit": "",
      "skype": "",
      "snapchat": "",
      "telegram": "",
      "whatsapp": "",
      "twitter": "",
      "vimeo": "",
      "youtube": "",
      "github": "",
      "crunchbase": "",
      "website_title": "",
      "website_generator": "",
      "website_description": "",
      "website_keywords": "",
      "website_has_fb_pixel": "",
      "website_has_google_tag": "",
      "primaryColor": "#9ad114",
      "secondaryColor": "#668b0d"
    },
    "fortner-plumbing": {
      "query": "plumber, 35745, Estillfork, AL, US",
      "name": "Fortner Plumbing",
      "name_for_emails": "Fortner Plumbing",
      "site": "",
      "subtypes": "Plumber, Service establishment",
      "category": "Plumber",
      "type": "Plumber",
      "phone": "+1 256-244-3030",
      "phone.phones_enricher.carrier_name": "NEW CINGULAR WIRELESS PCS, LLC - GA",
      "phone.phones_enricher.carrier_type": "mobile",
      "full_address": "",
      "borough": "",
      "street": "",
      "city": "",
      "postal_code": "",
      "state": "",
      "us_state": "",
      "country": "",
      "country_code": "",
      "latitude": "34.5490484",
      "longitude": "-86.396124",
      "h3": "8944eb20573ffff",
      "time_zone": "America/Chicago",
      "plus_code": "",
      "area_service": "TRUE",
      "rating": "5",
      "reviews": "1",
      "reviews_link": "https://search.google.com/local/reviews?placeid=ChIJMS0Zzfzm-kcRrofgE_ykHcY&q=plumber,+35745,+Estillfork,+AL,+US&authuser=0&hl=en&gl=US",
      "reviews_tags": "",
      "reviews_per_score": "",
      "reviews_per_score_1": "0",
      "reviews_per_score_2": "0",
      "reviews_per_score_3": "0",
      "reviews_per_score_4": "0",
      "reviews_per_score_5": "1",
      "photos_count": "5",
      "photo": "https://lh5.googleusercontent.com/p/AF1QipPtnJ28OmxqPJ4ngr8JjGEl0rWFkJ5LwYH5G31G=w800-h500-k-no",
      "street_view": "https://lh5.googleusercontent.com/p/AF1QipOJVQkHqiXJdPQgJZzghvejxStnxjKZ8BZFQlpL=w1600-h1000-k-no",
      "located_in": "",
      "working_hours": "{\"Monday\": \"6AM-6PM\", \"Tuesday\": \"6AM-6PM\", \"Wednesday\": \"6AM-6PM\", \"Thursday\": \"6AM-6PM\", \"Friday\": \"6AM-6PM\", \"Saturday\": \"8AM-12PM\", \"Sunday\": \"Closed\"}",
      "working_hours_old_format": "Monday:6AM-6PM|Tuesday:6AM-6PM|Wednesday:6AM-6PM|Thursday:6AM-6PM|Friday:6AM-6PM|Saturday:8AM-12PM|Sunday:Closed",
      "other_hours": "",
      "popular_times": "",
      "business_status": "OPERATIONAL",
      "about": "{}",
      "range": "",
      "posts": "",
      "logo": "https://lh4.googleusercontent.com/-UbxbsvJhqa8/AAAAAAAAAAI/AAAAAAAAAAA/T4I4sQGSYDI/photo.jpg",
      "description": "Fortner Plumbing is a small family owned plumbing business based out of Scottsboro Alabama. We travel to Jackson, Dekalb, Marshalls and Madison counties. We strive to bring the best plumbing services to you, and to help all of your plumbing needs. We specialize in residential and commercial work, repairing and installing septic tanks, and service work.",
      "typical_time_spent": "",
      "verified": "TRUE",
      "owner_id": "111060208822757483154",
      "owner_title": "Fortner Plumbing",
      "owner_link": "https://www.google.com/maps/contrib/111060208822757483154",
      "reservation_links": "",
      "booking_appointment_link": "",
      "menu_link": "",
      "order_links": "",
      "location_link": "https://www.google.com/maps/place/Fortner+Plumbing/@34.5490484,-86.396124,14z/data=!4m8!1m2!2m1!1sFortner+Plumbing!3m4!1s0x47fae6fccd192d31:0xc61da4fc13e087ae!8m2!3d34.5490484!4d-86.396124",
      "location_reviews_link": "https://www.google.com/maps/place/Fortner+Plumbing/@34.5490484,-86.396124,13.99z/data=!4m16!1m7!3m6!1s0x47fae6fccd192d31:0xc61da4fc13e087ae!2sFortner+Plumbing!8m2!3d34.5490484!4d-86.396124!16s%2Fg%2F11ckvg1dmb!3m7!1s0x47fae6fccd192d31:0xc61da4fc13e087ae!8m2!3d34.5490484!4d-86.396124!9m1!1b1!16s%2Fg%2F11ckvg1dmb?entry=ttu",
      "place_id": "ChIJMS0Zzfzm-kcRrofgE_ykHcY",
      "google_id": "0x47fae6fccd192d31:0xc61da4fc13e087ae",
      "cid": "1.42757E+19",
      "kgmid": "/g/11vr4ptb8s",
      "reviews_id": "-4170996277303015506",
      "located_google_id": "",
      "email_1": "",
      "email_1.emails_validator.status": "",
      "email_1.emails_validator.status_details": "",
      "email_1_full_name": "",
      "email_1_first_name": "",
      "email_1_last_name": "",
      "email_1_title": "",
      "email_1_phone": "",
      "email_2": "",
      "email_2.emails_validator.status": "",
      "email_2.emails_validator.status_details": "",
      "email_2_full_name": "",
      "email_2_first_name": "",
      "email_2_last_name": "",
      "email_2_title": "",
      "email_2_phone": "",
      "email_3": "",
      "email_3.emails_validator.status": "",
      "email_3.emails_validator.status_details": "",
      "email_3_full_name": "",
      "email_3_first_name": "",
      "email_3_last_name": "",
      "email_3_title": "",
      "email_3_phone": "",
      "phone_1": "",
      "phone_1.phones_enricher.carrier_name": "",
      "phone_1.phones_enricher.carrier_type": "",
      "phone_2": "",
      "phone_3": "",
      "facebook": "",
      "instagram": "",
      "linkedin": "",
      "tiktok": "",
      "medium": "",
      "reddit": "",
      "skype": "",
      "snapchat": "",
      "telegram": "",
      "whatsapp": "",
      "twitter": "",
      "vimeo": "",
      "youtube": "",
      "github": "",
      "crunchbase": "",
      "website_title": "",
      "website_generator": "",
      "website_description": "",
      "website_keywords": "",
      "website_has_fb_pixel": "",
      "website_has_google_tag": "",
      "primaryColor": "#9ad114",
      "secondaryColor": "#668b0d"
    },
    "joe-reid-dawes-plumbing-service": {
      "query": "plumber, 36568, Saint Elmo, AL, US",
      "name": "Joe Reid - Dawes Plumbing Service",
      "name_for_emails": "Joe Reid Dawes Plumbing Service",
      "site": "",
      "subtypes": "Plumber",
      "category": "Plumber",
      "type": "Plumber",
      "phone": "+1 251-401-0370",
      "phone.phones_enricher.carrier_name": "CELLCO PARTNERSHIP DBA VERIZON WIRELESS - AL",
      "phone.phones_enricher.carrier_type": "mobile",
      "full_address": "9373 Labrador Run S, Mobile, AL 36695",
      "borough": "Dawes",
      "street": "9373 Labrador Run S",
      "city": "Mobile",
      "postal_code": "36695",
      "state": "Alabama",
      "us_state": "Alabama",
      "country": "United States of America",
      "country_code": "US",
      "latitude": "30.6091382",
      "longitude": "-88.2626595",
      "h3": "89445017363ffff",
      "time_zone": "America/Chicago",
      "plus_code": "",
      "area_service": "FALSE",
      "rating": "4.9",
      "reviews": "18",
      "reviews_link": "https://search.google.com/local/reviews?placeid=ChIJ29szL0uxm4gRugrW7_NheWw&q=plumber,+36568,+Saint+Elmo,+AL,+US&authuser=0&hl=en&gl=US",
      "reviews_tags": "",
      "reviews_per_score": "",
      "reviews_per_score_1": "0",
      "reviews_per_score_2": "0",
      "reviews_per_score_3": "0",
      "reviews_per_score_4": "1",
      "reviews_per_score_5": "17",
      "photos_count": "5",
      "photo": "https://lh5.googleusercontent.com/p/AF1QipMi8gdswqTXB2qjW1WPpQHp9m6MPMFaapKtU6Et=w800-h500-k-no",
      "street_view": "https://lh5.googleusercontent.com/p/AF1QipMi8gdswqTXB2qjW1WPpQHp9m6MPMFaapKtU6Et=w1600-h1000-k-no",
      "located_in": "",
      "working_hours": "{\"Monday\": \"8AM-5PM\", \"Tuesday\": \"8AM-5PM\", \"Wednesday\": \"8AM-5PM\", \"Thursday\": \"8AM-5PM\", \"Friday\": \"8AM-5PM\", \"Saturday\": \"8AM-5PM\", \"Sunday\": \"Closed\"}",
      "working_hours_old_format": "Monday:8AM-5PM|Tuesday:8AM-5PM|Wednesday:8AM-5PM|Thursday:8AM-5PM|Friday:8AM-5PM|Saturday:8AM-5PM|Sunday:Closed",
      "other_hours": "",
      "popular_times": "",
      "business_status": "OPERATIONAL",
      "about": "{}",
      "range": "",
      "posts": "",
      "logo": "https://lh5.googleusercontent.com/-TFBtodnq-Ig/AAAAAAAAAAI/AAAAAAAAAAA/yzHjh0dctXI/photo.jpg",
      "description": "",
      "typical_time_spent": "",
      "verified": "TRUE",
      "owner_id": "102077258229252314857",
      "owner_title": "Joe Reid - Dawes Plumbing Service",
      "owner_link": "https://www.google.com/maps/contrib/102077258229252314857",
      "reservation_links": "",
      "booking_appointment_link": "",
      "menu_link": "",
      "order_links": "",
      "location_link": "https://www.google.com/maps/place/Joe+Reid+-+Dawes+Plumbing+Service/@30.6091382,-88.2626595,14z/data=!4m8!1m2!2m1!1sJoe+Reid+-+Dawes+Plumbing+Service!3m4!1s0x889bb14b2f33dbdb:0x6c7961f3efd60aba!8m2!3d30.6091382!4d-88.2626595",
      "location_reviews_link": "https://www.google.com/maps/place/Joe+Reid+-+Dawes+Plumbing+Service/@30.6091382,-88.2626595,13.99z/data=!4m16!1m7!3m6!1s0x889bb14b2f33dbdb:0x6c7961f3efd60aba!2sJoe+Reid+-+Dawes+Plumbing+Service!8m2!3d30.6091382!4d-88.2626595!16s%2Fg%2F11ckvg1dmb!3m7!1s0x889bb14b2f33dbdb:0x6c7961f3efd60aba!8m2!3d30.6091382!4d-88.2626595!9m1!1b1!16s%2Fg%2F11ckvg1dmb?entry=ttu",
      "place_id": "ChIJ29szL0uxm4gRugrW7_NheWw",
      "google_id": "0x889bb14b2f33dbdb:0x6c7961f3efd60aba",
      "cid": "7.81639E+18",
      "kgmid": "/g/11fxxw_rp6",
      "reviews_id": "7816386328606935738",
      "located_google_id": "",
      "email_1": "",
      "email_1.emails_validator.status": "",
      "email_1.emails_validator.status_details": "",
      "email_1_full_name": "",
      "email_1_first_name": "",
      "email_1_last_name": "",
      "email_1_title": "",
      "email_1_phone": "",
      "email_2": "",
      "email_2.emails_validator.status": "",
      "email_2.emails_validator.status_details": "",
      "email_2_full_name": "",
      "email_2_first_name": "",
      "email_2_last_name": "",
      "email_2_title": "",
      "email_2_phone": "",
      "email_3": "",
      "email_3.emails_validator.status": "",
      "email_3.emails_validator.status_details": "",
      "email_3_full_name": "",
      "email_3_first_name": "",
      "email_3_last_name": "",
      "email_3_title": "",
      "email_3_phone": "",
      "phone_1": "",
      "phone_1.phones_enricher.carrier_name": "",
      "phone_1.phones_enricher.carrier_type": "",
      "phone_2": "",
      "phone_3": "",
      "facebook": "",
      "instagram": "",
      "linkedin": "",
      "tiktok": "",
      "medium": "",
      "reddit": "",
      "skype": "",
      "snapchat": "",
      "telegram": "",
      "whatsapp": "",
      "twitter": "",
      "vimeo": "",
      "youtube": "",
      "github": "",
      "crunchbase": "",
      "website_title": "",
      "website_generator": "",
      "website_description": "",
      "website_keywords": "",
      "website_has_fb_pixel": "",
      "website_has_google_tag": "",
      "primaryColor": "#9ad114",
      "secondaryColor": "#668b0d"
    },
    "brian-harden-plumbing-inc": {
      "query": "plumber, 36581, Sunflower, AL, US",
      "name": "Brian Harden Plumbing Inc.",
      "name_for_emails": "Brian Harden Plumbing",
      "site": "",
      "subtypes": "Plumber",
      "category": "Plumber",
      "type": "Plumber",
      "phone": "+1 251-973-2234",
      "phone.phones_enricher.carrier_name": "",
      "phone.phones_enricher.carrier_type": "mobile",
      "full_address": "7465 Oak Dr W, Theodore, AL 36582",
      "borough": "Bellmont",
      "street": "7465 Oak Dr W",
      "city": "Theodore",
      "postal_code": "36582",
      "state": "Alabama",
      "us_state": "Alabama",
      "country": "United States of America",
      "country_code": "US",
      "latitude": "30.5356351",
      "longitude": "-88.1992606",
      "h3": "89445010187ffff",
      "time_zone": "America/Chicago",
      "plus_code": "",
      "area_service": "FALSE",
      "rating": "5",
      "reviews": "2",
      "reviews_link": "https://search.google.com/local/reviews?placeid=ChIJ7U09VnK1m4gRzof1GJ1x-r4&q=plumber,+36581,+Sunflower,+AL,+US&authuser=0&hl=en&gl=US",
      "reviews_tags": "",
      "reviews_per_score": "",
      "reviews_per_score_1": "0",
      "reviews_per_score_2": "0",
      "reviews_per_score_3": "0",
      "reviews_per_score_4": "0",
      "reviews_per_score_5": "2",
      "photos_count": "5",
      "photo": "https://lh5.googleusercontent.com/p/AF1QipOJUqILlQWWNEU3AvlqEVc5yAw6lL3-7bfyyYvY=w800-h500-k-no",
      "street_view": "https://lh5.googleusercontent.com/p/AF1QipOJUqILlQWWNEU3AvlqEVc5yAw6lL3-7bfyyYvY=w1600-h1000-k-no",
      "located_in": "",
      "working_hours": "{\"Monday\": \"8AM-6PM\", \"Tuesday\": \"8AM-6PM\", \"Wednesday\": \"8AM-6PM\", \"Thursday\": \"8AM-6PM\", \"Friday\": \"8AM-6PM\", \"Saturday\": \"8AM-12PM\", \"Sunday\": \"Closed\"}",
      "working_hours_old_format": "Monday:8AM-6PM|Tuesday:8AM-6PM|Wednesday:8AM-6PM|Thursday:8AM-6PM|Friday:8AM-6PM|Saturday:8AM-12PM|Sunday:Closed",
      "other_hours": "",
      "popular_times": "",
      "business_status": "OPERATIONAL",
      "about": "{\"Payments\": {\"Credit cards\": true}}",
      "range": "",
      "posts": "",
      "logo": "https://lh3.googleusercontent.com/-YIDfUdb9y3s/AAAAAAAAAAI/AAAAAAAAAAA/0DZs7EpM5ds/photo.jpg",
      "description": "",
      "typical_time_spent": "",
      "verified": "TRUE",
      "owner_id": "106557637042471268588",
      "owner_title": "Brian Harden Plumbing Inc.",
      "owner_link": "https://www.google.com/maps/contrib/106557637042471268588",
      "reservation_links": "",
      "booking_appointment_link": "",
      "menu_link": "",
      "order_links": "",
      "location_link": "https://www.google.com/maps/place/Brian+Harden+Plumbing+Inc./@30.5356351,-88.1992606,14z/data=!4m8!1m2!2m1!1sBrian+Harden+Plumbing+Inc.!3m4!1s0x889bb572563d4ded:0xbefa719d18f587ce!8m2!3d30.5356351!4d-88.1992606",
      "location_reviews_link": "https://www.google.com/maps/place/Brian+Harden+Plumbing+Inc./@30.5356351,-88.1992606,13.99z/data=!4m16!1m7!3m6!1s0x889bb572563d4ded:0xbefa719d18f587ce!2sBrian+Harden+Plumbing+Inc.!8m2!3d30.5356351!4d-88.1992606!16s%2Fg%2F11ckvg1dmb!3m7!1s0x889bb572563d4ded:0xbefa719d18f587ce!8m2!3d30.5356351!4d-88.1992606!9m1!1b1!16s%2Fg%2F11ckvg1dmb?entry=ttu",
      "place_id": "ChIJ7U09VnK1m4gRzof1GJ1x-r4",
      "google_id": "0x889bb572563d4ded:0xbefa719d18f587ce",
      "cid": "1.37614E+19",
      "kgmid": "/g/1tfdzmvd",
      "reviews_id": "-4685307542783031346",
      "located_google_id": "",
      "email_1": "",
      "email_1.emails_validator.status": "",
      "email_1.emails_validator.status_details": "",
      "email_1_full_name": "",
      "email_1_first_name": "",
      "email_1_last_name": "",
      "email_1_title": "",
      "email_1_phone": "",
      "email_2": "",
      "email_2.emails_validator.status": "",
      "email_2.emails_validator.status_details": "",
      "email_2_full_name": "",
      "email_2_first_name": "",
      "email_2_last_name": "",
      "email_2_title": "",
      "email_2_phone": "",
      "email_3": "",
      "email_3.emails_validator.status": "",
      "email_3.emails_validator.status_details": "",
      "email_3_full_name": "",
      "email_3_first_name": "",
      "email_3_last_name": "",
      "email_3_title": "",
      "email_3_phone": "",
      "phone_1": "",
      "phone_1.phones_enricher.carrier_name": "",
      "phone_1.phones_enricher.carrier_type": "",
      "phone_2": "",
      "phone_3": "",
      "facebook": "",
      "instagram": "",
      "linkedin": "",
      "tiktok": "",
      "medium": "",
      "reddit": "",
      "skype": "",
      "snapchat": "",
      "telegram": "",
      "whatsapp": "",
      "twitter": "",
      "vimeo": "",
      "youtube": "",
      "github": "",
      "crunchbase": "",
      "website_title": "",
      "website_generator": "",
      "website_description": "",
      "website_keywords": "",
      "website_has_fb_pixel": "",
      "website_has_google_tag": "",
      "primaryColor": "#9ad114",
      "secondaryColor": "#668b0d"
    },
    "a-c-e-plumbing-solutions": {
      "query": "plumber, 36477, Samson, AL, US",
      "name": "A.C.E. Plumbing Solutions",
      "name_for_emails": "A C E Plumbing Solutions",
      "site": "",
      "subtypes": "Plumber, Service establishment",
      "category": "Plumber",
      "type": "Plumber",
      "phone": "+1 850-865-9607",
      "phone.phones_enricher.carrier_name": "CELLCO PARTNERSHIP DBA VERIZON WIRELESS - FL",
      "phone.phones_enricher.carrier_type": "mobile",
      "full_address": "",
      "borough": "",
      "street": "",
      "city": "",
      "postal_code": "",
      "state": "",
      "us_state": "",
      "country": "",
      "country_code": "",
      "latitude": "30.6044959",
      "longitude": "-86.32263",
      "h3": "8944e522a47ffff",
      "time_zone": "America/Chicago",
      "plus_code": "",
      "area_service": "TRUE",
      "rating": "5",
      "reviews": "25",
      "reviews_link": "https://search.google.com/local/reviews?placeid=ChIJ1SnXvb0WHCQRRRzL0uKBx6s&q=plumber,+36477,+Samson,+AL,+US&authuser=0&hl=en&gl=US",
      "reviews_tags": "",
      "reviews_per_score": "",
      "reviews_per_score_1": "0",
      "reviews_per_score_2": "0",
      "reviews_per_score_3": "0",
      "reviews_per_score_4": "0",
      "reviews_per_score_5": "25",
      "photos_count": "5",
      "photo": "https://lh5.googleusercontent.com/p/AF1QipNrDpAY_Oj90ySO6fsk6IoONqsQYJe1KJdbS-53=w800-h500-k-no",
      "street_view": "https://lh5.googleusercontent.com/p/AF1QipNrDpAY_Oj90ySO6fsk6IoONqsQYJe1KJdbS-53=w1600-h1000-k-no",
      "located_in": "",
      "working_hours": "{\"Monday\": \"7AM-5PM\", \"Tuesday\": \"7AM-5PM\", \"Wednesday\": \"7AM-5PM\", \"Thursday\": \"7AM-5PM\", \"Friday\": \"7AM-5PM\", \"Saturday\": \"Closed\", \"Sunday\": \"Closed\"}",
      "working_hours_old_format": "Monday:7AM-5PM|Tuesday:7AM-5PM|Wednesday:7AM-5PM|Thursday:7AM-5PM|Friday:7AM-5PM|Saturday:Closed|Sunday:Closed",
      "other_hours": "",
      "popular_times": "",
      "business_status": "OPERATIONAL",
      "about": "{\"Payments\": {\"Credit cards\": true}}",
      "range": "",
      "posts": "",
      "logo": "https://lh4.googleusercontent.com/-dqH2g87lSps/AAAAAAAAAAI/AAAAAAAAAAA/CkHxosl1J5g/photo.jpg",
      "description": "",
      "typical_time_spent": "",
      "verified": "TRUE",
      "owner_id": "105706093729290984912",
      "owner_title": "A.C.E. Plumbing Solutions",
      "owner_link": "https://www.google.com/maps/contrib/105706093729290984912",
      "reservation_links": "",
      "booking_appointment_link": "",
      "menu_link": "",
      "order_links": "",
      "location_link": "https://www.google.com/maps/place/A.C.E.+Plumbing+Solutions/@30.6044959,-86.32262999999999,14z/data=!4m8!1m2!2m1!1sA.C.E.+Plumbing+Solutions!3m4!1s0x241c16bdbdd729d5:0xabc781e2d2cb1c45!8m2!3d30.6044959!4d-86.32262999999999",
      "location_reviews_link": "https://www.google.com/maps/place/A.C.E.+Plumbing+Solutions/@30.6044959,-86.32262999999999,13.99z/data=!4m16!1m7!3m6!1s0x241c16bdbdd729d5:0xabc781e2d2cb1c45!2sA.C.E.+Plumbing+Solutions!8m2!3d30.6044959!4d-86.32262999999999!16s%2Fg%2F11ckvg1dmb!3m7!1s0x241c16bdbdd729d5:0xabc781e2d2cb1c45!8m2!3d30.6044959!4d-86.32262999999999!9m1!1b1!16s%2Fg%2F11ckvg1dmb?entry=ttu",
      "place_id": "ChIJ1SnXvb0WHCQRRRzL0uKBx6s",
      "google_id": "0x241c16bdbdd729d5:0xabc781e2d2cb1c45",
      "cid": "1.2378E+19",
      "kgmid": "/g/11w8yr0g8w",
      "reviews_id": "-6068739161659335611",
      "located_google_id": "",
      "email_1": "",
      "email_1.emails_validator.status": "",
      "email_1.emails_validator.status_details": "",
      "email_1_full_name": "",
      "email_1_first_name": "",
      "email_1_last_name": "",
      "email_1_title": "",
      "email_1_phone": "",
      "email_2": "",
      "email_2.emails_validator.status": "",
      "email_2.emails_validator.status_details": "",
      "email_2_full_name": "",
      "email_2_first_name": "",
      "email_2_last_name": "",
      "email_2_title": "",
      "email_2_phone": "",
      "email_3": "",
      "email_3.emails_validator.status": "",
      "email_3.emails_validator.status_details": "",
      "email_3_full_name": "",
      "email_3_first_name": "",
      "email_3_last_name": "",
      "email_3_title": "",
      "email_3_phone": "",
      "phone_1": "",
      "phone_1.phones_enricher.carrier_name": "",
      "phone_1.phones_enricher.carrier_type": "",
      "phone_2": "",
      "phone_3": "",
      "facebook": "",
      "instagram": "",
      "linkedin": "",
      "tiktok": "",
      "medium": "",
      "reddit": "",
      "skype": "",
      "snapchat": "",
      "telegram": "",
      "whatsapp": "",
      "twitter": "",
      "vimeo": "",
      "youtube": "",
      "github": "",
      "crunchbase": "",
      "website_title": "",
      "website_generator": "",
      "website_description": "",
      "website_keywords": "",
      "website_has_fb_pixel": "",
      "website_has_google_tag": "",
      "primaryColor": "#9ad114",
      "secondaryColor": "#668b0d"
    },
    "quality-plumbing-co": {
      "query": "plumber, 35175, Union Grove, AL, US",
      "name": "Quality Plumbing Co.",
      "name_for_emails": "Quality Plumbing",
      "site": "",
      "subtypes": "Plumber",
      "category": "Plumber",
      "type": "Plumber",
      "phone": "+1 256-738-5625",
      "phone.phones_enricher.carrier_name": "NEW CINGULAR WIRELESS PCS, LLC - GA",
      "phone.phones_enricher.carrier_type": "mobile",
      "full_address": "2577 Union Grove Rd, Union Grove, AL 35175",
      "borough": "None",
      "street": "2577 Union Grove Rd",
      "city": "Union Grove",
      "postal_code": "35175",
      "state": "Alabama",
      "us_state": "Alabama",
      "country": "United States of America",
      "country_code": "US",
      "latitude": "34.391467",
      "longitude": "-86.4298714",
      "h3": "8944eb30553ffff",
      "time_zone": "America/Chicago",
      "plus_code": "",
      "area_service": "FALSE",
      "rating": "5",
      "reviews": "1",
      "reviews_link": "https://search.google.com/local/reviews?placeid=ChIJqUsqKDvjiYgRMzj_18zTZ10&q=plumber,+35175,+Union+Grove,+AL,+US&authuser=0&hl=en&gl=US",
      "reviews_tags": "",
      "reviews_per_score": "",
      "reviews_per_score_1": "0",
      "reviews_per_score_2": "0",
      "reviews_per_score_3": "0",
      "reviews_per_score_4": "0",
      "reviews_per_score_5": "1",
      "photos_count": "5",
      "photo": "https://lh5.googleusercontent.com/p/AF1QipPRL0AiLbxNlh5LPs0xa2Abl357bz8Cz3ab9s9W=w800-h500-k-no",
      "street_view": "https://lh5.googleusercontent.com/p/AF1QipPRL0AiLbxNlh5LPs0xa2Abl357bz8Cz3ab9s9W=w1600-h1000-k-no",
      "located_in": "",
      "working_hours": "",
      "working_hours_old_format": "",
      "other_hours": "",
      "popular_times": "",
      "business_status": "CLOSED_PERMANENTLY",
      "about": "{}",
      "range": "",
      "posts": "",
      "logo": "https://lh3.googleusercontent.com/-E6bV0yftMFU/AAAAAAAAAAI/AAAAAAAAAAA/cSO7_tCfh_U/photo.jpg",
      "description": "",
      "typical_time_spent": "",
      "verified": "TRUE",
      "owner_id": "112763030291974969585",
      "owner_title": "Quality Plumbing Co.",
      "owner_link": "https://www.google.com/maps/contrib/112763030291974969585",
      "reservation_links": "",
      "booking_appointment_link": "",
      "menu_link": "",
      "order_links": "",
      "location_link": "https://www.google.com/maps/place/Quality+Plumbing+Co./@34.391467,-86.4298714,14z/data=!4m8!1m2!2m1!1sQuality+Plumbing+Co.!3m4!1s0x8889e33b282a4ba9:0x5d67d3ccd7ff3833!8m2!3d34.391467!4d-86.4298714",
      "location_reviews_link": "https://www.google.com/maps/place/Quality+Plumbing+Co./@34.391467,-86.4298714,13.99z/data=!4m16!1m7!3m6!1s0x8889e33b282a4ba9:0x5d67d3ccd7ff3833!2sQuality+Plumbing+Co.!8m2!3d34.391467!4d-86.4298714!16s%2Fg%2F11ckvg1dmb!3m7!1s0x8889e33b282a4ba9:0x5d67d3ccd7ff3833!8m2!3d34.391467!4d-86.4298714!9m1!1b1!16s%2Fg%2F11ckvg1dmb?entry=ttu",
      "place_id": "ChIJqUsqKDvjiYgRMzj_18zTZ10",
      "google_id": "0x8889e33b282a4ba9:0x5d67d3ccd7ff3833",
      "cid": "6.73058E+18",
      "kgmid": "/g/11q85tghd4",
      "reviews_id": "6730581044879112243",
      "located_google_id": "",
      "email_1": "",
      "email_1.emails_validator.status": "",
      "email_1.emails_validator.status_details": "",
      "email_1_full_name": "",
      "email_1_first_name": "",
      "email_1_last_name": "",
      "email_1_title": "",
      "email_1_phone": "",
      "email_2": "",
      "email_2.emails_validator.status": "",
      "email_2.emails_validator.status_details": "",
      "email_2_full_name": "",
      "email_2_first_name": "",
      "email_2_last_name": "",
      "email_2_title": "",
      "email_2_phone": "",
      "email_3": "",
      "email_3.emails_validator.status": "",
      "email_3.emails_validator.status_details": "",
      "email_3_full_name": "",
      "email_3_first_name": "",
      "email_3_last_name": "",
      "email_3_title": "",
      "email_3_phone": "",
      "phone_1": "",
      "phone_1.phones_enricher.carrier_name": "",
      "phone_1.phones_enricher.carrier_type": "",
      "phone_2": "",
      "phone_3": "",
      "facebook": "",
      "instagram": "",
      "linkedin": "",
      "tiktok": "",
      "medium": "",
      "reddit": "",
      "skype": "",
      "snapchat": "",
      "telegram": "",
      "whatsapp": "",
      "twitter": "",
      "vimeo": "",
      "youtube": "",
      "github": "",
      "crunchbase": "",
      "website_title": "",
      "website_generator": "",
      "website_description": "",
      "website_keywords": "",
      "website_has_fb_pixel": "",
      "website_has_google_tag": "",
      "primaryColor": "#9ad114",
      "secondaryColor": "#668b0d"
    },
    "boydstun-plumbing-llc": {
      "query": "plumber, 35614, Athens, AL, US",
      "name": "Boydstun Plumbing LLC",
      "name_for_emails": "Boydstun Plumbing",
      "site": "",
      "subtypes": "Plumber, Service establishment",
      "category": "Plumber",
      "type": "Plumber",
      "phone": "+1 256-400-9606",
      "phone.phones_enricher.carrier_name": "",
      "phone.phones_enricher.carrier_type": "",
      "full_address": "",
      "borough": "",
      "street": "",
      "city": "",
      "postal_code": "",
      "state": "",
      "us_state": "",
      "country": "",
      "country_code": "",
      "latitude": "34.7540101",
      "longitude": "-86.760846",
      "h3": "89264932e9bffff",
      "time_zone": "America/Chicago",
      "plus_code": "",
      "area_service": "TRUE",
      "rating": "5",
      "reviews": "6",
      "reviews_link": "https://search.google.com/local/reviews?placeid=ChIJU2euNoRnYogRFJlGAQtnCqo&q=plumber,+35614,+Athens,+AL,+US&authuser=0&hl=en&gl=US",
      "reviews_tags": "",
      "reviews_per_score": "",
      "reviews_per_score_1": "0",
      "reviews_per_score_2": "0",
      "reviews_per_score_3": "0",
      "reviews_per_score_4": "0",
      "reviews_per_score_5": "6",
      "photos_count": "5",
      "photo": "https://lh5.googleusercontent.com/p/AF1QipNP6PS0Etyx8qDZfU4_eFMldCuxXXeSKi-x_GFf=w800-h500-k-no",
      "street_view": "https://lh5.googleusercontent.com/p/AF1QipNP6PS0Etyx8qDZfU4_eFMldCuxXXeSKi-x_GFf=w1600-h1000-k-no",
      "located_in": "",
      "working_hours": "{\"Monday\": \"8AM-5PM\", \"Tuesday\": \"8AM-5PM\", \"Wednesday\": \"8AM-5PM\", \"Thursday\": \"8AM-5PM\", \"Friday\": \"8AM-5PM\", \"Saturday\": \"8AM-5PM\", \"Sunday\": \"8AM-5PM\"}",
      "working_hours_old_format": "Monday:8AM-5PM|Tuesday:8AM-5PM|Wednesday:8AM-5PM|Thursday:8AM-5PM|Friday:8AM-5PM|Saturday:8AM-5PM|Sunday:8AM-5PM",
      "other_hours": "",
      "popular_times": "",
      "business_status": "OPERATIONAL",
      "about": "{\"Service options\": {\"Online estimates\": false}, \"Planning\": {\"Appointment required\": true}}",
      "range": "",
      "posts": "",
      "logo": "https://lh6.googleusercontent.com/-WIsufaUP28I/AAAAAAAAAAI/AAAAAAAAAAA/6uc3O2gRWeQ/photo.jpg",
      "description": "",
      "typical_time_spent": "",
      "verified": "TRUE",
      "owner_id": "112243250103978490830",
      "owner_title": "Boydstun Plumbing LLC",
      "owner_link": "https://www.google.com/maps/contrib/112243250103978490830",
      "reservation_links": "",
      "booking_appointment_link": "https://www.boydstunplumbing.com/contact/",
      "menu_link": "",
      "order_links": "https://www.boydstunplumbing.com/contact/",
      "location_link": "https://www.google.com/maps/place/Boydstun+Plumbing+LLC/@34.754010099999995,-86.760846,14z/data=!4m8!1m2!2m1!1sBoydstun+Plumbing+LLC!3m4!1s0x8862678436ae6753:0xaa0a670b01469914!8m2!3d34.754010099999995!4d-86.760846",
      "location_reviews_link": "https://www.google.com/maps/place/Boydstun+Plumbing+LLC/@34.754010099999995,-86.760846,13.99z/data=!4m16!1m7!3m6!1s0x8862678436ae6753:0xaa0a670b01469914!2sBoydstun+Plumbing+LLC!8m2!3d34.754010099999995!4d-86.760846!16s%2Fg%2F11ckvg1dmb!3m7!1s0x8862678436ae6753:0xaa0a670b01469914!8m2!3d34.754010099999995!4d-86.760846!9m1!1b1!16s%2Fg%2F11ckvg1dmb?entry=ttu",
      "place_id": "ChIJU2euNoRnYogRFJlGAQtnCqo",
      "google_id": "0x8862678436ae6753:0xaa0a670b01469914",
      "cid": "1.22527E+19",
      "kgmid": "/g/11sybxsqmx",
      "reviews_id": "-6194025040530990828",
      "located_google_id": "",
      "email_1": "",
      "email_1.emails_validator.status": "",
      "email_1.emails_validator.status_details": "",
      "email_1_full_name": "",
      "email_1_first_name": "",
      "email_1_last_name": "",
      "email_1_title": "",
      "email_1_phone": "",
      "email_2": "",
      "email_2.emails_validator.status": "",
      "email_2.emails_validator.status_details": "",
      "email_2_full_name": "",
      "email_2_first_name": "",
      "email_2_last_name": "",
      "email_2_title": "",
      "email_2_phone": "",
      "email_3": "",
      "email_3.emails_validator.status": "",
      "email_3.emails_validator.status_details": "",
      "email_3_full_name": "",
      "email_3_first_name": "",
      "email_3_last_name": "",
      "email_3_title": "",
      "email_3_phone": "",
      "phone_1": "",
      "phone_1.phones_enricher.carrier_name": "",
      "phone_1.phones_enricher.carrier_type": "",
      "phone_2": "",
      "phone_3": "",
      "facebook": "",
      "instagram": "",
      "linkedin": "",
      "tiktok": "",
      "medium": "",
      "reddit": "",
      "skype": "",
      "snapchat": "",
      "telegram": "",
      "whatsapp": "",
      "twitter": "",
      "vimeo": "",
      "youtube": "",
      "github": "",
      "crunchbase": "",
      "website_title": "",
      "website_generator": "",
      "website_description": "",
      "website_keywords": "",
      "website_has_fb_pixel": "",
      "website_has_google_tag": "",
      "primaryColor": "#9ad114",
      "secondaryColor": "#668b0d"
    },
    "barnett-plumbing-llc": {
      "query": "plumber, 35617, Cloverdale, AL, US",
      "name": "Barnett Plumbing, LLC",
      "name_for_emails": "Barnett Plumbing",
      "site": "",
      "subtypes": "Plumber",
      "category": "Plumber",
      "type": "Plumber",
      "phone": "+1 256-740-6776",
      "phone.phones_enricher.carrier_name": "",
      "phone.phones_enricher.carrier_type": "",
      "full_address": "875 Sweetwater Ave, Florence, AL 35630",
      "borough": "East Florence",
      "street": "875 Sweetwater Ave",
      "city": "Florence",
      "postal_code": "35630",
      "state": "Alabama",
      "us_state": "Alabama",
      "country": "United States of America",
      "country_code": "US",
      "latitude": "34.8215879",
      "longitude": "-87.6471163",
      "h3": "8926494d107ffff",
      "time_zone": "America/Chicago",
      "plus_code": "",
      "area_service": "FALSE",
      "rating": "4.4",
      "reviews": "61",
      "reviews_link": "https://search.google.com/local/reviews?placeid=ChIJtTDOR8ZJfYgRwDLojseuzrE&q=plumber,+35617,+Cloverdale,+AL,+US&authuser=0&hl=en&gl=US",
      "reviews_tags": "",
      "reviews_per_score": "",
      "reviews_per_score_1": "7",
      "reviews_per_score_2": "1",
      "reviews_per_score_3": "0",
      "reviews_per_score_4": "3",
      "reviews_per_score_5": "50",
      "photos_count": "5",
      "photo": "https://lh5.googleusercontent.com/p/AF1QipPQS08N2fUUG6o3_7F2Lp2c0TT01A5TuDAu9fNX=w800-h500-k-no",
      "street_view": "https://lh5.googleusercontent.com/p/AF1QipPQS08N2fUUG6o3_7F2Lp2c0TT01A5TuDAu9fNX=w1600-h1000-k-no",
      "located_in": "",
      "working_hours": "{\"Monday\": \"8AM-5PM\", \"Tuesday\": \"8AM-5PM\", \"Wednesday\": \"8AM-5PM\", \"Thursday\": \"8AM-5PM\", \"Friday\": \"8AM-5PM\", \"Saturday\": \"Closed\", \"Sunday\": \"Closed\"}",
      "working_hours_old_format": "Monday:8AM-5PM|Tuesday:8AM-5PM|Wednesday:8AM-5PM|Thursday:8AM-5PM|Friday:8AM-5PM|Saturday:Closed|Sunday:Closed",
      "other_hours": "",
      "popular_times": "",
      "business_status": "OPERATIONAL",
      "about": "{\"Accessibility\": {\"Wheelchair accessible entrance\": true}, \"Offerings\": {\"Repair services\": true}, \"Payments\": {\"Credit cards\": true}}",
      "range": "",
      "posts": "",
      "logo": "https://lh3.googleusercontent.com/-GtG3XANxcqY/AAAAAAAAAAI/AAAAAAAAAAA/ajL1MPN_j0Y/photo.jpg",
      "description": "",
      "typical_time_spent": "",
      "verified": "TRUE",
      "owner_id": "100113749103245685567",
      "owner_title": "Barnett Plumbing, LLC",
      "owner_link": "https://www.google.com/maps/contrib/100113749103245685567",
      "reservation_links": "",
      "booking_appointment_link": "",
      "menu_link": "",
      "order_links": "",
      "location_link": "https://www.google.com/maps/place/Barnett+Plumbing%2C+LLC/@34.8215879,-87.6471163,14z/data=!4m8!1m2!2m1!1sBarnett+Plumbing%2C+LLC!3m4!1s0x887d49c647ce30b5:0xb1ceaec78ee832c0!8m2!3d34.8215879!4d-87.6471163",
      "location_reviews_link": "https://www.google.com/maps/place/Barnett+Plumbing%2C+LLC/@34.8215879,-87.6471163,13.99z/data=!4m16!1m7!3m6!1s0x887d49c647ce30b5:0xb1ceaec78ee832c0!2sBarnett+Plumbing%2C+LLC!8m2!3d34.8215879!4d-87.6471163!16s%2Fg%2F11ckvg1dmb!3m7!1s0x887d49c647ce30b5:0xb1ceaec78ee832c0!8m2!3d34.8215879!4d-87.6471163!9m1!1b1!16s%2Fg%2F11ckvg1dmb?entry=ttu",
      "place_id": "ChIJtTDOR8ZJfYgRwDLojseuzrE",
      "google_id": "0x887d49c647ce30b5:0xb1ceaec78ee832c0",
      "cid": "1.28124E+19",
      "kgmid": "/g/11f4pnp918",
      "reviews_id": "-5634373911674604864",
      "located_google_id": "",
      "email_1": "",
      "email_1.emails_validator.status": "",
      "email_1.emails_validator.status_details": "",
      "email_1_full_name": "",
      "email_1_first_name": "",
      "email_1_last_name": "",
      "email_1_title": "",
      "email_1_phone": "",
      "email_2": "",
      "email_2.emails_validator.status": "",
      "email_2.emails_validator.status_details": "",
      "email_2_full_name": "",
      "email_2_first_name": "",
      "email_2_last_name": "",
      "email_2_title": "",
      "email_2_phone": "",
      "email_3": "",
      "email_3.emails_validator.status": "",
      "email_3.emails_validator.status_details": "",
      "email_3_full_name": "",
      "email_3_first_name": "",
      "email_3_last_name": "",
      "email_3_title": "",
      "email_3_phone": "",
      "phone_1": "",
      "phone_1.phones_enricher.carrier_name": "",
      "phone_1.phones_enricher.carrier_type": "",
      "phone_2": "",
      "phone_3": "",
      "facebook": "",
      "instagram": "",
      "linkedin": "",
      "tiktok": "",
      "medium": "",
      "reddit": "",
      "skype": "",
      "snapchat": "",
      "telegram": "",
      "whatsapp": "",
      "twitter": "",
      "vimeo": "",
      "youtube": "",
      "github": "",
      "crunchbase": "",
      "website_title": "",
      "website_generator": "",
      "website_description": "",
      "website_keywords": "",
      "website_has_fb_pixel": "",
      "website_has_google_tag": "",
      "primaryColor": "#9ad114",
      "secondaryColor": "#668b0d"
    },
    "morrison-plumbing": {
      "query": "plumber, 35078, Harpersville, AL, US",
      "name": "Morrison Plumbing",
      "name_for_emails": "Morrison Plumbing",
      "site": "",
      "subtypes": "Plumber, Service establishment",
      "category": "Plumber",
      "type": "Plumber",
      "phone": "+1 205-678-8084",
      "phone.phones_enricher.carrier_name": "",
      "phone.phones_enricher.carrier_type": "",
      "full_address": "",
      "borough": "",
      "street": "",
      "city": "",
      "postal_code": "",
      "state": "",
      "us_state": "",
      "country": "",
      "country_code": "",
      "latitude": "32.5762265",
      "longitude": "-86.6807364",
      "h3": "8944e89300fffff",
      "time_zone": "America/Chicago",
      "plus_code": "",
      "area_service": "TRUE",
      "rating": "5",
      "reviews": "6",
      "reviews_link": "https://search.google.com/local/reviews?placeid=ChIJlbD4yhVpiYgRIczjr_o8mo4&q=plumber,+35078,+Harpersville,+AL,+US&authuser=0&hl=en&gl=US",
      "reviews_tags": "",
      "reviews_per_score": "",
      "reviews_per_score_1": "0",
      "reviews_per_score_2": "0",
      "reviews_per_score_3": "0",
      "reviews_per_score_4": "0",
      "reviews_per_score_5": "6",
      "photos_count": "5",
      "photo": "https://lh5.googleusercontent.com/p/AF1QipNTiTIwYqKljrtwb2ROgrRm0fKqUO-kPParPwCI=w800-h500-k-no",
      "street_view": "https://lh5.googleusercontent.com/p/AF1QipNTiTIwYqKljrtwb2ROgrRm0fKqUO-kPParPwCI=w1600-h1000-k-no",
      "located_in": "",
      "working_hours": "{\"Monday\": \"8AM-4:30PM\", \"Tuesday\": \"8AM-4:30PM\", \"Wednesday\": \"8AM-4:30PM\", \"Thursday\": \"8AM-4:30PM\", \"Friday\": \"8AM-4:30PM\", \"Saturday\": \"Closed\", \"Sunday\": \"Closed\"}",
      "working_hours_old_format": "Monday:8AM-4:30PM|Tuesday:8AM-4:30PM|Wednesday:8AM-4:30PM|Thursday:8AM-4:30PM|Friday:8AM-4:30PM|Saturday:Closed|Sunday:Closed",
      "other_hours": "",
      "popular_times": "",
      "business_status": "OPERATIONAL",
      "about": "{}",
      "range": "",
      "posts": "",
      "logo": "https://lh5.googleusercontent.com/-wL0Gxxv6H7M/AAAAAAAAAAI/AAAAAAAAAAA/PuKbzycW2kY/photo.jpg",
      "description": "",
      "typical_time_spent": "",
      "verified": "TRUE",
      "owner_id": "103886819527159745797",
      "owner_title": "Morrison Plumbing",
      "owner_link": "https://www.google.com/maps/contrib/103886819527159745797",
      "reservation_links": "",
      "booking_appointment_link": "",
      "menu_link": "",
      "order_links": "",
      "location_link": "https://www.google.com/maps/place/Morrison+Plumbing/@32.5762265,-86.6807364,14z/data=!4m8!1m2!2m1!1sMorrison+Plumbing!3m4!1s0x88896915caf8b095:0x8e9a3cfaafe3cc21!8m2!3d32.5762265!4d-86.6807364",
      "location_reviews_link": "https://www.google.com/maps/place/Morrison+Plumbing/@32.5762265,-86.6807364,13.99z/data=!4m16!1m7!3m6!1s0x88896915caf8b095:0x8e9a3cfaafe3cc21!2sMorrison+Plumbing!8m2!3d32.5762265!4d-86.6807364!16s%2Fg%2F11ckvg1dmb!3m7!1s0x88896915caf8b095:0x8e9a3cfaafe3cc21!8m2!3d32.5762265!4d-86.6807364!9m1!1b1!16s%2Fg%2F11ckvg1dmb?entry=ttu",
      "place_id": "ChIJlbD4yhVpiYgRIczjr_o8mo4",
      "google_id": "0x88896915caf8b095:0x8e9a3cfaafe3cc21",
      "cid": "1.02756E+19",
      "kgmid": "/g/1v831wfk",
      "reviews_id": "-8171151526519911391",
      "located_google_id": "",
      "email_1": "",
      "email_1.emails_validator.status": "",
      "email_1.emails_validator.status_details": "",
      "email_1_full_name": "",
      "email_1_first_name": "",
      "email_1_last_name": "",
      "email_1_title": "",
      "email_1_phone": "",
      "email_2": "",
      "email_2.emails_validator.status": "",
      "email_2.emails_validator.status_details": "",
      "email_2_full_name": "",
      "email_2_first_name": "",
      "email_2_last_name": "",
      "email_2_title": "",
      "email_2_phone": "",
      "email_3": "",
      "email_3.emails_validator.status": "",
      "email_3.emails_validator.status_details": "",
      "email_3_full_name": "",
      "email_3_first_name": "",
      "email_3_last_name": "",
      "email_3_title": "",
      "email_3_phone": "",
      "phone_1": "",
      "phone_1.phones_enricher.carrier_name": "",
      "phone_1.phones_enricher.carrier_type": "",
      "phone_2": "",
      "phone_3": "",
      "facebook": "",
      "instagram": "",
      "linkedin": "",
      "tiktok": "",
      "medium": "",
      "reddit": "",
      "skype": "",
      "snapchat": "",
      "telegram": "",
      "whatsapp": "",
      "twitter": "",
      "vimeo": "",
      "youtube": "",
      "github": "",
      "crunchbase": "",
      "website_title": "",
      "website_generator": "",
      "website_description": "",
      "website_keywords": "",
      "website_has_fb_pixel": "",
      "website_has_google_tag": "",
      "primaryColor": "#9ad114",
      "secondaryColor": "#668b0d"
    }
  },
  "forceUpdateTimestamp": "1737001800.4230201"
}